secret_detect/__init__.py
secret_detect/scanner.py
secrets_detection-0.1.3.dist-info/LICENSE
secrets_detection-0.1.3.dist-info/METADATA
secrets_detection-0.1.3.dist-info/WHEEL
secrets_detection-0.1.3.dist-info/entry_points.txt
secrets_detection-0.1.3.dist-info/top_level.txt
secrets_detection-0.1.3.dist-info/RECORD
