Metadata-Version: 2.1
Name: secrets-detection
Version: 0.1.3
Summary: A package for use in detecting secrets leaks in the GitLab pipeline.
Home-page: https://github.com/Boyinf/secrets-detection/
Author: boyinf
License: MIT
Classifier: Programming Language :: Python :: 3
Classifier: License :: OSI Approved :: MIT License
Classifier: Operating System :: OS Independent
License-File: LICENSE
